riverqueue/__init__.py
riverqueue/client.py
riverqueue/fnv.py
riverqueue/insert_opts.py
riverqueue/job.py
riverqueue/py.typed
riverqueue/driver/__init__.py
riverqueue/driver/driver_protocol.py
riverqueue/driver/riversqlalchemy/__init__.py
riverqueue/driver/riversqlalchemy/sql_alchemy_driver.py
riverqueue/driver/riversqlalchemy/dbsqlc/models.py
riverqueue/driver/riversqlalchemy/dbsqlc/pg_misc.py
riverqueue/driver/riversqlalchemy/dbsqlc/pg_misc.sql
riverqueue/driver/riversqlalchemy/dbsqlc/river_job.py
riverqueue/driver/riversqlalchemy/dbsqlc/river_job.sql
riverqueue/driver/riversqlalchemy/dbsqlc/sqlc.yaml
riverqueue-0.7.0.dist-info/METADATA
riverqueue-0.7.0.dist-info/WHEEL
riverqueue-0.7.0.dist-info/licenses/LICENSE
riverqueue-0.7.0.dist-info/RECORD
