Metadata-Version: 2.3
Name: riverqueue
Version: 0.7.0
Summary: Python insert-only client for River.
Project-URL: Changelog, https://github.com/riverqueue/riverqueue-python/blob/master/CHANGELOG.md
Project-URL: Documentation, https://riverqueue.com/docs
Project-URL: Homepage, https://riverqueue.com
Project-URL: Issues, https://github.com/riverqueue/riverqueue-python/issues
Project-URL: Repository, https://github.com/riverqueue/riverqueue-python.git
Author-email: Eric Hauser <ewhauser@gmail.com>, Brandur Leach <brandur@brandur.org>
License-File: LICENSE
Requires-Python: >=3.8
Requires-Dist: sqlalchemy>=2.0.30
